rtl/instruction_memory.v
module instruction_memory(
    input  wire [31:0] addr,
    output wire [31:0] instruction
);

    reg [31:0] memory [0:255];

    initial begin
        // Example Program

        // addi x1, x0, 5
        memory[0] = 32'h00500093;

        // addi x2, x0, 10
        memory[1] = 32'h00A00113;

        // add x3, x1, x2
        memory[2] = 32'h002081B3;

        // nop
        memory[3] = 32'h00000013;
    end

    // Word aligned access
    assign instruction = memory[addr[31:2]];

endmodule

rtl/fetch_stage.v
module fetch_stage(
    input  wire        clk,
    input  wire        rst_n,

    output wire [31:0] pc_out,
    output wire [31:0] instruction_out
);

    reg [31:0] pc;

    wire [31:0] instruction;

    instruction_memory imem (
        .addr(pc),
        .instruction(instruction)
    );

    always @(posedge clk or negedge rst_n)
    begin
        if (!rst_n)
            pc <= 32'b0;
        else
            pc <= pc + 32'd4;
    end

    assign pc_out = pc;
    assign instruction_out = instruction;

endmodule

tb/fetch_stage_tb.v
`timescale 1ns/1ps

module fetch_stage_tb;

    reg clk;
    reg rst_n;

    wire [31:0] pc_out;
    wire [31:0] instruction_out;

    fetch_stage DUT(
        .clk(clk),
        .rst_n(rst_n),
        .pc_out(pc_out),
        .instruction_out(instruction_out)
    );

    always #5 clk = ~clk;

    initial begin

        $dumpfile("fetch_stage.vcd");
        $dumpvars(0, fetch_stage_tb);

        clk = 0;
        rst_n = 0;

        #20;
        rst_n = 1;

        #100;

        $finish;
    end

endmodule

fetch_stage.vcd
$date
	Mon Jun  8 23:31:32 2026
$end
$version
	Icarus Verilog
$end
$timescale
	1ps
$end
$scope module fetch_stage_tb $end
$var wire 32 ! pc_out [31:0] $end
$var wire 32 " instruction_out [31:0] $end
$var reg 1 # clk $end
$var reg 1 $ rst_n $end
$scope module DUT $end
$var wire 1 # clk $end
$var wire 32 % instruction_out [31:0] $end
$var wire 32 & pc_out [31:0] $end
$var wire 1 $ rst_n $end
$var wire 32 ' instruction [31:0] $end
$var reg 32 ( pc [31:0] $end
$scope module imem $end
$var wire 32 ) addr [31:0] $end
$var wire 32 * instruction [31:0] $end
$upscope $end
$upscope $end
$upscope $end
$enddefinitions $end
$comment Show the parameter values. $end
$dumpall
$end
#0
$dumpvars
b10100000000000010010011 *
b0 )
b0 (
b10100000000000010010011 '
b0 &
b10100000000000010010011 %
0$
0#
b10100000000000010010011 "
b0 !
$end
#5000
1#
#10000
0#
#15000
1#
#20000
0#
1$
#25000
b101000000000000100010011 "
b101000000000000100010011 %
b101000000000000100010011 '
b101000000000000100010011 *
b100 !
b100 &
b100 (
b100 )
1#
#30000
0#
#35000
b1000001000000110110011 "
b1000001000000110110011 %
b1000001000000110110011 '
b1000001000000110110011 *
b1000 !
b1000 &
b1000 (
b1000 )
1#
#40000
0#
#45000
b10011 "
b10011 %
b10011 '
b10011 *
b1100 !
b1100 &
b1100 (
b1100 )
1#
#50000
0#
#55000
bx "
bx %
bx '
bx *
b10000 !
b10000 &
b10000 (
b10000 )
1#
#60000
0#
#65000
b10100 !
b10100 &
b10100 (
b10100 )
1#
#70000
0#
#75000
b11000 !
b11000 &
b11000 (
b11000 )
1#
#80000
0#
#85000
b11100 !
b11100 &
b11100 (
b11100 )
1#
#90000
0#
#95000
b100000 !
b100000 &
b100000 (
b100000 )
1#
#100000
0#
#105000
b100100 !
b100100 &
b100100 (
b100100 )
1#
#110000
0#
#115000
b101000 !
b101000 &
b101000 (
b101000 )
1#
