rtl/register_file.v
module register_file(
    input  wire        clk,
    input  wire        rst_n,

    // Read Port 1
    input  wire [4:0]  rs1_addr,
    output wire [31:0] rs1_data,

    // Read Port 2
    input  wire [4:0]  rs2_addr,
    output wire [31:0] rs2_data,

    // Write Port
    input  wire        reg_write,
    input  wire [4:0]  rd_addr,
    input  wire [31:0] rd_data
);

    reg [31:0] registers [0:31];

    integer i;

    // Reset + Write Logic
    always @(posedge clk or negedge rst_n)
    begin
        if(!rst_n)
        begin
            for(i = 0; i < 32; i = i + 1)
                registers[i] <= 32'b0;
        end
        else
        begin
            // x0 is hardwired to zero
            if(reg_write && (rd_addr != 5'd0))
                registers[rd_addr] <= rd_data;
        end
    end

    // Asynchronous Reads
    assign rs1_data = (rs1_addr == 5'd0) ?
                      32'b0 :
                      registers[rs1_addr];

    assign rs2_data = (rs2_addr == 5'd0) ?
                      32'b0 :
                      registers[rs2_addr];

endmodule

tb/register_file_tb.v
`timescale 1ns/1ps

module register_file_tb;

    reg clk;
    reg rst_n;

    reg [4:0] rs1_addr;
    reg [4:0] rs2_addr;

    wire [31:0] rs1_data;
    wire [31:0] rs2_data;

    reg reg_write;
    reg [4:0] rd_addr;
    reg [31:0] rd_data;

    register_file DUT(
        .clk(clk),
        .rst_n(rst_n),

        .rs1_addr(rs1_addr),
        .rs1_data(rs1_data),

        .rs2_addr(rs2_addr),
        .rs2_data(rs2_data),

        .reg_write(reg_write),
        .rd_addr(rd_addr),
        .rd_data(rd_data)
    );

    always #5 clk = ~clk;

    initial begin

        $dumpfile("register_file.vcd");
        $dumpvars(0, register_file_tb);

        clk = 0;
        rst_n = 0;

        rs1_addr = 0;
        rs2_addr = 0;

        reg_write = 0;
        rd_addr = 0;
        rd_data = 0;

        #20;
        rst_n = 1;

        // Write x5 = 100
        #10;
        reg_write = 1;
        rd_addr = 5;
        rd_data = 100;

        #10;
        reg_write = 0;

        // Read x5
        rs1_addr = 5;

        #20;

        // Attempt to write x0
        reg_write = 1;
        rd_addr = 0;
        rd_data = 999;

        #10;
        reg_write = 0;

        rs1_addr = 0;

        #20;

        $finish;
    end

endmodule

register_file.vcd
$date
	Mon Jun  8 23:34:50 2026
$end
$version
	Icarus Verilog
$end
$timescale
	1ps
$end
$scope module register_file_tb $end
$var wire 32 ! rs2_data [31:0] $end
$var wire 32 " rs1_data [31:0] $end
$var reg 1 # clk $end
$var reg 5 $ rd_addr [4:0] $end
$var reg 32 % rd_data [31:0] $end
$var reg 1 & reg_write $end
$var reg 5 ' rs1_addr [4:0] $end
$var reg 5 ( rs2_addr [4:0] $end
$var reg 1 ) rst_n $end
$scope module DUT $end
$var wire 1 # clk $end
$var wire 5 * rd_addr [4:0] $end
$var wire 32 + rd_data [31:0] $end
$var wire 1 & reg_write $end
$var wire 5 , rs1_addr [4:0] $end
$var wire 5 - rs2_addr [4:0] $end
$var wire 1 ) rst_n $end
$var wire 32 . rs2_data [31:0] $end
$var wire 32 / rs1_data [31:0] $end
$var integer 32 0 i [31:0] $end
$upscope $end
$upscope $end
$enddefinitions $end
$comment Show the parameter values. $end
$dumpall
$end
#0
$dumpvars
b100000 0
b0 /
b0 .
b0 -
b0 ,
b0 +
b0 *
0)
b0 (
b0 '
0&
b0 %
b0 $
0#
b0 "
b0 !
$end
#5000
b100000 0
1#
#10000
0#
#15000
b100000 0
1#
#20000
0#
1)
#25000
1#
#30000
0#
b1100100 %
b1100100 +
b101 $
b101 *
1&
#35000
1#
#40000
b1100100 "
b1100100 /
0#
b101 '
b101 ,
0&
#45000
1#
#50000
0#
#55000
1#
#60000
0#
b1111100111 %
b1111100111 +
b0 $
b0 *
1&
#65000
1#
#70000
b0 "
b0 /
0#
b0 '
b0 ,
0&
